rafiki/__init__.py
rafiki/rafiki.py
rafiki/utils.py
rafiki-0.4.3.dist-info/DESCRIPTION.rst
rafiki-0.4.3.dist-info/METADATA
rafiki-0.4.3.dist-info/metadata.json
rafiki-0.4.3.dist-info/RECORD
rafiki-0.4.3.dist-info/top_level.txt
rafiki-0.4.3.dist-info/WHEEL
