Metadata-Version: 2.0
Name: rafiki
Version: 0.4.3
Summary: Library to read/write raf format used in League of Legends
Home-page: https://github.com/tnajdek/rafiki
Author: Tom Najdek
Author-email: tom@doppnet.com
License: MIT
Platform: UNKNOWN
Classifier: Development Status :: 4 - Beta
Classifier: License :: OSI Approved :: MIT License
Classifier: Programming Language :: Python :: 2
Classifier: Programming Language :: Python :: 2.7
Classifier: Programming Language :: Python :: 3
Classifier: Programming Language :: Python :: 3.3
Classifier: Programming Language :: Python :: 3.4
Requires-Dist: future
